{
  "_note": "Per-team display metadata not in the DB. Keyed by Team.name. Missing teams fall back to abbr=first 3 letters and stripe=--accent. Fill in over time.",
  "Ohio State": { "abbr": "OSU", "mascot": "Buckeyes", "primary": "#bb0000", "secondary": "#666666" },
  "Georgia": { "abbr": "UGA", "mascot": "Bulldogs", "primary": "#ba0c2f", "secondary": "#000000" },
  "Texas": { "abbr": "TEX", "mascot": "Longhorns", "primary": "#bf5700", "secondary": "#ffffff" },
  "Oregon": { "abbr": "ORE", "mascot": "Ducks", "primary": "#154733", "secondary": "#fee123" },
  "Alabama": { "abbr": "ALA", "mascot": "Crimson Tide", "primary": "#9e1b32", "secondary": "#828a8f" },
  "Notre Dame": { "abbr": "ND", "mascot": "Fighting Irish", "primary": "#0c2340", "secondary": "#c99700" },
  "Tennessee": { "abbr": "TENN", "mascot": "Volunteers", "primary": "#ff8200", "secondary": "#58595b" },
  "Michigan": { "abbr": "MICH", "mascot": "Wolverines", "primary": "#00274c", "secondary": "#ffcb05" },
  "Penn State": { "abbr": "PSU", "mascot": "Nittany Lions", "primary": "#041e42", "secondary": "#ffffff" },
  "Ole Miss": { "abbr": "MISS", "mascot": "Rebels", "primary": "#ce1126", "secondary": "#14213d" },
  "Miami": { "abbr": "MIA", "mascot": "Hurricanes", "primary": "#f47321", "secondary": "#005030" },
  "LSU": { "abbr": "LSU", "mascot": "Tigers", "primary": "#461d7c", "secondary": "#fdd023" },
  "Clemson": { "abbr": "CLEM", "mascot": "Tigers", "primary": "#f56600", "secondary": "#522d80" },
  "Indiana": { "abbr": "IND", "mascot": "Hoosiers", "primary": "#990000", "secondary": "#ffffff" },
  "Oklahoma": { "abbr": "OU", "mascot": "Sooners", "primary": "#841617", "secondary": "#fdf9d8" },
  "Kansas State": { "abbr": "KSU", "mascot": "Wildcats", "primary": "#512888", "secondary": "#a7a7a7" },
  "Texas A&M": { "abbr": "TAMU", "mascot": "Aggies", "primary": "#500000", "secondary": "#ffffff" },
  "Louisville": { "abbr": "LOU", "mascot": "Cardinals", "primary": "#ad0000", "secondary": "#000000" },
  "Utah": { "abbr": "UTAH", "mascot": "Utes", "primary": "#cc0000", "secondary": "#808080" },
  "BYU": { "abbr": "BYU", "mascot": "Cougars", "primary": "#002e5d", "secondary": "#ffffff" },
  "Iowa State": { "abbr": "ISU", "mascot": "Cyclones", "primary": "#c8102e", "secondary": "#f1be48" },
  "South Carolina": { "abbr": "SC", "mascot": "Gamecocks", "primary": "#73000a", "secondary": "#000000" },
  "Florida": { "abbr": "FLA", "mascot": "Gators", "primary": "#0021a5", "secondary": "#fa4616" },
  "Florida State": { "abbr": "FSU", "mascot": "Seminoles", "primary": "#782f40", "secondary": "#ceb888" },
  "Auburn": { "abbr": "AUB", "mascot": "Tigers", "primary": "#0c2340", "secondary": "#dd550c" },
  "Wisconsin": { "abbr": "WIS", "mascot": "Badgers", "primary": "#c5050c", "secondary": "#ffffff" },
  "Iowa": { "abbr": "IOWA", "mascot": "Hawkeyes", "primary": "#ffcd00", "secondary": "#000000" },
  "Washington": { "abbr": "WASH", "mascot": "Huskies", "primary": "#4b2e83", "secondary": "#b7a57a" },
  "USC": { "abbr": "USC", "mascot": "Trojans", "primary": "#990000", "secondary": "#ffc72c" },
  "Nebraska": { "abbr": "NEB", "mascot": "Cornhuskers", "primary": "#e41c38", "secondary": "#ffffff" },
  "Missouri": { "abbr": "MIZ", "mascot": "Tigers", "primary": "#f1b82d", "secondary": "#000000" },
  "Kansas": { "abbr": "KU", "mascot": "Jayhawks", "primary": "#0051ba", "secondary": "#e8000d" },
  "SMU": { "abbr": "SMU", "mascot": "Mustangs", "primary": "#0033a0", "secondary": "#c8102e" },
  "Boise State": { "abbr": "BSU", "mascot": "Broncos", "primary": "#0033a0", "secondary": "#d64309" }
}
